hyperhyy/__init__.py
hyperhyy/cli.py
hyperhyy/core/__init__.py
hyperhyy/core/connection_pool.py
hyperhyy/core/proxy_server.py
hyperhyy/core/tls_handler.py
hyperhyy/utils/__init__.py
hyperhyy/utils/config.py
hyperhyy/utils/logger.py
hyperhyy-0.1.0.dist-info/METADATA
hyperhyy-0.1.0.dist-info/WHEEL
hyperhyy-0.1.0.dist-info/entry_points.txt
hyperhyy-0.1.0.dist-info/top_level.txt
hyperhyy-0.1.0.dist-info/RECORD
