Metadata-Version: 2.2
Name: hyperhyy
Version: 0.1.0
Author: Huang Yiyi
Author-email: 363766687@qq.com
Classifier: Development Status :: 3 - Alpha
Classifier: Intended Audience :: Developers
Classifier: License :: OSI Approved :: MIT License
Classifier: Programming Language :: Python :: 3.8
Requires-Python: >=3.6
Requires-Dist: requests>=2.26.0
Requires-Dist: PyYAML>=5.4.1
Requires-Dist: cryptography
Requires-Dist: pyOpenSSL
Requires-Dist: brotli
Requires-Dist: uvloop
Requires-Dist: python-snappy
Dynamic: author
Dynamic: author-email
Dynamic: classifier
Dynamic: requires-dist
Dynamic: requires-python
